<?xml version="1.0" encoding="UTF-8" standalone="no"?><WIG20><ALR><Ticker>ALR</Ticker><Nazwa>ALIOR</Nazwa><PełnaNazwa>Alior Bank SA</PełnaNazwa><Link>http://www.bankier.pl/inwestowanie/profile/quote.html?symbol=ALIOR</Link><LinkArchiwum>http://www.biznesradar.pl/notowania-historyczne/ALIOR</LinkArchiwum></ALR><ACP><Ticker>ACP</Ticker><Nazwa>ASSECOPOL</Nazwa><PełnaNazwa>Asseco Poland SA</PełnaNazwa><Link>http://www.bankier.pl/inwestowanie/profile/quote.html?symbol=ASSECOPOL</Link><LinkArchiwum>http://www.biznesradar.pl/notowania-historyczne/ASSECOPOL</LinkArchiwum></ACP><BZW><Ticker>BZW</Ticker><Nazwa>BZWBK</Nazwa><PełnaNazwa>Bank Zachodni WBK SA</PełnaNazwa><Link>http://www.bankier.pl/inwestowanie/profile/quote.html?symbol=BZWBK</Link><LinkArchiwum>http://www.biznesradar.pl/notowania-historyczne/BZWBK</LinkArchiwum></BZW><CCC><Ticker>CCC</Ticker><Nazwa>CCC</Nazwa><PełnaNazwa>CCC S.A.</PełnaNazwa><Link>http://www.bankier.pl/inwestowanie/profile/quote.html?symbol=CCC</Link><LinkArchiwum>http://www.biznesradar.pl/notowania-historyczne/CCC</LinkArchiwum></CCC><CPS><Ticker>CPS</Ticker><Nazwa>CYFRPLSAT</Nazwa><PełnaNazwa>Cyfrowy Polsat SA</PełnaNazwa><Link>http://www.bankier.pl/inwestowanie/profile/quote.html?symbol=CYFRPLSAT</Link><LinkArchiwum>http://www.biznesradar.pl/notowania-historyczne/CYFRPLSAT</LinkArchiwum></CPS><ENA><Ticker>ENA</Ticker><Nazwa>ENEA</Nazwa><PełnaNazwa>ENEA SA</PełnaNazwa><Link>http://www.bankier.pl/inwestowanie/profile/quote.html?symbol=ENEA</Link><LinkArchiwum>http://www.biznesradar.pl/notowania-historyczne/ENEA</LinkArchiwum></ENA><ENG><Ticker>ENG</Ticker><Nazwa>ENERGA</Nazwa><PełnaNazwa>Energa S.A.</PełnaNazwa><Link>http://www.bankier.pl/inwestowanie/profile/quote.html?symbol=ENERGA</Link><LinkArchiwum>http://www.biznesradar.pl/notowania-historyczne/ENERGA</LinkArchiwum></ENG><EUR><Ticker>EUR</Ticker><Nazwa>EUROCASH</Nazwa><PełnaNazwa>Eurocash SA</PełnaNazwa><Link>http://www.bankier.pl/inwestowanie/profile/quote.html?symbol=EUROCASH</Link><LinkArchiwum>http://www.biznesradar.pl/notowania-historyczne/EUROCASH</LinkArchiwum></EUR><KGH><Ticker>KGH</Ticker><Nazwa>KGHM</Nazwa><PełnaNazwa>KGHM Polska Miedź SA</PełnaNazwa><Link>http://www.bankier.pl/inwestowanie/profile/quote.html?symbol=KGHM</Link><LinkArchiwum>http://www.biznesradar.pl/notowania-historyczne/KGHM</LinkArchiwum></KGH><LTS><Ticker>LTS</Ticker><Nazwa>LOTOS</Nazwa><PełnaNazwa>Grupa LOTOS SA</PełnaNazwa><Link>http://www.bankier.pl/inwestowanie/profile/quote.html?symbol=LOTOS</Link><LinkArchiwum>http://www.biznesradar.pl/notowania-historyczne/LOTOS</LinkArchiwum></LTS><LPP><Ticker>LPP</Ticker><Nazwa>LPP</Nazwa><PełnaNazwa>LPP SA</PełnaNazwa><Link>http://www.bankier.pl/inwestowanie/profile/quote.html?symbol=LPP</Link><LinkArchiwum>http://www.biznesradar.pl/notowania-historyczne/LPP</LinkArchiwum></LPP><MBK><Ticker>MBK</Ticker><Nazwa>MBANK</Nazwa><PełnaNazwa>mBank S.A.</PełnaNazwa><Link>http://www.bankier.pl/inwestowanie/profile/quote.html?symbol=MBANK</Link><LinkArchiwum>http://www.biznesradar.pl/notowania-historyczne/MBANK</LinkArchiwum></MBK><OPL><Ticker>OPL</Ticker><Nazwa>ORANGEPL</Nazwa><PełnaNazwa>Orange Polska S.A.</PełnaNazwa><Link>http://www.bankier.pl/inwestowanie/profile/quote.html?symbol=ORANGEPL</Link><LinkArchiwum>http://www.biznesradar.pl/notowania-historyczne/ORANGEPL</LinkArchiwum></OPL><PEO><Ticker>PEO</Ticker><Nazwa>PEKAO</Nazwa><PełnaNazwa>Bank Polska Kasa Opieki SA</PełnaNazwa><Link>http://www.bankier.pl/inwestowanie/profile/quote.html?symbol=PEKAO</Link><LinkArchiwum>http://www.biznesradar.pl/notowania-historyczne/PEKAO</LinkArchiwum></PEO><PGE><Ticker>PGE</Ticker><Nazwa>PGE</Nazwa><PełnaNazwa>Polska Grupa Energetyczna SA</PełnaNazwa><Link>http://www.bankier.pl/inwestowanie/profile/quote.html?symbol=PGE</Link><LinkArchiwum>http://www.biznesradar.pl/notowania-historyczne/PGE</LinkArchiwum></PGE><PGN><Ticker>PGN</Ticker><Nazwa>PGNIG</Nazwa><PełnaNazwa>Polskie Górnictwo Naftowe i Gazownictwo SA</PełnaNazwa><Link>http://www.bankier.pl/inwestowanie/profile/quote.html?symbol=PGNIG</Link><LinkArchiwum>http://www.biznesradar.pl/notowania-historyczne/PGNIG</LinkArchiwum></PGN><PKN><Ticker>PKN</Ticker><Nazwa>PKNORLEN</Nazwa><PełnaNazwa>Polski Koncern Naftowy ORLEN SA</PełnaNazwa><Link>http://www.bankier.pl/inwestowanie/profile/quote.html?symbol=PKNORLEN</Link><LinkArchiwum>http://www.biznesradar.pl/notowania-historyczne/PKNORLEN</LinkArchiwum></PKN><PKO><Ticker>PKO</Ticker><Nazwa>PKOBP</Nazwa><PełnaNazwa>Powszechna Kasa Oszczędności Bank Polski SA</PełnaNazwa><Link>http://www.bankier.pl/inwestowanie/profile/quote.html?symbol=PKOBP</Link><LinkArchiwum>http://www.biznesradar.pl/notowania-historyczne/PKOBP</LinkArchiwum></PKO><PZU><Ticker>PZU</Ticker><Nazwa>PZU</Nazwa><PełnaNazwa>Powszechny Zakład Ubezpieczeń SA</PełnaNazwa><Link>http://www.bankier.pl/inwestowanie/profile/quote.html?symbol=PZU</Link><LinkArchiwum>http://www.biznesradar.pl/notowania-historyczne/PZU</LinkArchiwum></PZU><TPE><Ticker>TPE</Ticker><Nazwa>TAURONPE</Nazwa><PełnaNazwa>Tauron Polska Energia SA</PełnaNazwa><Link>http://www.bankier.pl/inwestowanie/profile/quote.html?symbol=TAURONPE</Link><LinkArchiwum>http://www.biznesradar.pl/notowania-historyczne/TAURONPE</LinkArchiwum></TPE></WIG20>